feishuBot/__init__.py
feishuBot/request.py
feishuBot/route.py
feishuBot/server.py
feishuBot/utils.py
feishuBot/event/__init__.py
feishuBot/event/im/__init__.py
feishuBot/event/im/message/__init__.py
feishuBot/event/im/message/receive_v1.py
PYfeishuBot-0.0.2.dist-info/LICENSE
PYfeishuBot-0.0.2.dist-info/METADATA
PYfeishuBot-0.0.2.dist-info/WHEEL
PYfeishuBot-0.0.2.dist-info/top_level.txt
PYfeishuBot-0.0.2.dist-info/RECORD
